{
  "hash": "8ec13fda",
  "configHash": "f595317e",
  "lockfileHash": "e3b0c442",
  "browserHash": "73948f29",
  "optimized": {
    "@chakra-ui/react": {
      "src": "../../node_modules/@chakra-ui/react/dist/index.mjs",
      "file": "@chakra-ui_react.js",
      "fileHash": "204ae53b",
      "needsInterop": false
    },
    "@chakra-ui/theme-tools": {
      "src": "../../node_modules/@chakra-ui/theme-tools/dist/index.mjs",
      "file": "@chakra-ui_theme-tools.js",
      "fileHash": "dcea4bc5",
      "needsInterop": false
    },
    "react": {
      "src": "../../node_modules/react/index.js",
      "file": "react.js",
      "fileHash": "30324801",
      "needsInterop": true
    },
    "react-dom/client": {
      "src": "../../node_modules/react-dom/client.js",
      "file": "react-dom_client.js",
      "fileHash": "0129fc17",
      "needsInterop": true
    },
    "react-icons/fa": {
      "src": "../../node_modules/react-icons/fa/index.mjs",
      "file": "react-icons_fa.js",
      "fileHash": "50f2ea70",
      "needsInterop": false
    },
    "react-icons/hi": {
      "src": "../../node_modules/react-icons/hi/index.mjs",
      "file": "react-icons_hi.js",
      "fileHash": "6e03ded0",
      "needsInterop": false
    },
    "react-router-dom": {
      "src": "../../node_modules/react-router-dom/dist/index.js",
      "file": "react-router-dom.js",
      "fileHash": "7ca7f482",
      "needsInterop": false
    }
  },
  "chunks": {
    "chunk-BHDLHQY3": {
      "file": "chunk-BHDLHQY3.js"
    },
    "chunk-FBRNPY62": {
      "file": "chunk-FBRNPY62.js"
    },
    "chunk-PEH4OUYE": {
      "file": "chunk-PEH4OUYE.js"
    },
    "chunk-UM3JHGVO": {
      "file": "chunk-UM3JHGVO.js"
    },
    "chunk-CEQRFMJQ": {
      "file": "chunk-CEQRFMJQ.js"
    }
  }
}